quickargtypes/qat.py
quickargtypes-0.1.0.dist-info/LICENSE
quickargtypes-0.1.0.dist-info/METADATA
quickargtypes-0.1.0.dist-info/WHEEL
quickargtypes-0.1.0.dist-info/top_level.txt
quickargtypes-0.1.0.dist-info/RECORD
