Metadata-Version: 2.1
Name: quickargtypes
Version: 0.1.0
Summary: Argument parsing types for the argparse library
Home-page: https://github.com/KadenMc/quickargtypes
Author: Kaden McKeen
Author-email: kaden.mckeen@mail.utoronto.ca
License: MIT
Platform: UNKNOWN
